LICENSE
README.md
setup.py
rl_jitai_simulation/__init__.py
rl_jitai_simulation/agents.py
rl_jitai_simulation/envs.py
rl_jitai_simulation/utils.py
rljitai.egg-info/PKG-INFO
rljitai.egg-info/SOURCES.txt
rljitai.egg-info/dependency_links.txt
rljitai.egg-info/entry_points.txt
rljitai.egg-info/requires.txt
rljitai.egg-info/top_level.txt